way2smswrapper/__init__.py
way2smswrapper/wrapper.py
way2smswrapper-0.1.2.dist-info/LICENSE
way2smswrapper-0.1.2.dist-info/WHEEL
way2smswrapper-0.1.2.dist-info/METADATA
way2smswrapper-0.1.2.dist-info/RECORD
